python_debugger_mcp/__init__.py
python_debugger_mcp/main.py
python_debugger_mcp-0.4.0.dist-info/METADATA
python_debugger_mcp-0.4.0.dist-info/WHEEL
python_debugger_mcp-0.4.0.dist-info/entry_points.txt
python_debugger_mcp-0.4.0.dist-info/RECORD
