Metadata-Version: 2.4
Name: python-debugger-mcp
Version: 0.4.0
Summary: Model Context Protocol server for Python debugging with AI assistants
Project-URL: Homepage, https://github.com/yourusername/python-debugger-mcp
Project-URL: Repository, https://github.com/yourusername/python-debugger-mcp
Project-URL: Issues, https://github.com/yourusername/python-debugger-mcp/issues
Author-email: samefarrar <67292186+samefarrar@users.noreply.github.com>
License: MIT
Keywords: ai,claude,debugger,debugging,llm,mcp,pdb,python
Classifier: Development Status :: 4 - Beta
Classifier: Intended Audience :: Developers
Classifier: License :: OSI Approved :: MIT License
Classifier: Operating System :: OS Independent
Classifier: Programming Language :: Python :: 3
Classifier: Programming Language :: Python :: 3.10
Classifier: Programming Language :: Python :: 3.11
Classifier: Programming Language :: Python :: 3.12
Classifier: Programming Language :: Python :: 3.13
Classifier: Topic :: Software Development :: Debuggers
Classifier: Topic :: Software Development :: Libraries :: Python Modules
Requires-Python: >=3.10
Requires-Dist: mcp[cli]>=1.6.0
Provides-Extra: test
Requires-Dist: packaging>=21.0; extra == 'test'
Requires-Dist: pytest-asyncio>=0.21.0; extra == 'test'
Requires-Dist: pytest-cov>=4.0.0; extra == 'test'
Requires-Dist: pytest-mock>=3.10.0; extra == 'test'
Requires-Dist: pytest>=7.0.0; extra == 'test'
